Missing/__init__.py
Missing/missing.py
Missing_Data_101703402-0.0.1.dist-info/LICENSE
Missing_Data_101703402-0.0.1.dist-info/METADATA
Missing_Data_101703402-0.0.1.dist-info/WHEEL
Missing_Data_101703402-0.0.1.dist-info/top_level.txt
Missing_Data_101703402-0.0.1.dist-info/RECORD
